nandini/__init__.py
nandini/models/__init__.py
nandini/models/liner_model.py
nandini/sequence/__init__.py
nandini/sequence/gensim_vectorizers.py
nandini/sequence/text.py
nandini-0.0.5.dist-info/METADATA
nandini-0.0.5.dist-info/WHEEL
nandini-0.0.5.dist-info/top_level.txt
nandini-0.0.5.dist-info/RECORD
