Metadata-Version: 2.1
Name: nandini
Version: 0.0.5
Summary: A Scratch Module for Machine learning
Home-page: 
Author: Sanjaypranav
Author-email: sanjaypriya195@gmail.com
Classifier: Programming Language :: Python :: 3
Classifier: License :: OSI Approved :: MIT License
Classifier: Operating System :: OS Independent
Requires-Python: >=3.7,<=3.10.6
Requires-Dist: numpy (~=1.23.2)
Requires-Dist: regex
Requires-Dist: tqdm (~=4.64.1)
Requires-Dist: joblib (~=1.1.0)
Requires-Dist: nltk (~=3.7)
Requires-Dist: progressbar (~=2.5)
Requires-Dist: scipy (~=1.9.1)
Requires-Dist: gensim (~=4.2.0)
